/**
 * @file j2me_interpreter_optimized.c
 * @brief ä¼˜åŒ–çš„J2MEå­—èŠ‚ç è§£é‡Šå™¨å®ç°
 * 
 * é«˜æ€§èƒ½å­—èŠ‚ç è§£é‡Šå™¨ï¼ŒåŒ…å«ä»¥ä¸‹ä¼˜åŒ–:
 * - æŒ‡ä»¤é¢„è§£ç å’Œç¼“å­˜
 * - è·³è½¬è¡¨ä¼˜åŒ–çš„æŒ‡ä»¤åˆ†å‘
 * - å†…è”ç¼“å­˜çš„æ–¹æ³•è°ƒç”¨
 * - çƒ­ç‚¹æ£€æµ‹å’Œæ‰¹é‡æ‰§è¡Œ
 * - æ€§èƒ½ç›‘æ§å’Œç»Ÿè®¡
 */

#include "j2me_interpreter_optimized.h"
#include "j2me_bytecode.h"
#include "j2me_vm.h"
#include "j2me_native_methods.h"
#include <stdlib.h>
#include <string.h>
#include <stdio.h>
#include <time.h>

// è·å–å½“å‰æ—¶é—´æˆ³ (å¾®ç§’)
static j2me_long get_current_time_us(void) {
    struct timespec ts;
    clock_gettime(CLOCK_MONOTONIC, &ts);
    return ts.tv_sec * 1000000LL + ts.tv_nsec / 1000;
}

// æŒ‡ä»¤å¤„ç†å‡½æ•°è·³è½¬è¡¨
static j2me_instruction_handler_t instruction_handlers[256] = {0};

// åˆå§‹åŒ–æŒ‡ä»¤å¤„ç†å‡½æ•°è·³è½¬è¡¨
static void initialize_instruction_handlers(void) {
    static j2me_boolean initialized = false;
    if (initialized) return;
    
    // åŸºç¡€æŒ‡ä»¤
    instruction_handlers[0x00] = j2me_handle_nop;           // nop
    instruction_handlers[0x01] = j2me_handle_iconst;        // aconst_null
    instruction_handlers[0x02] = j2me_handle_iconst;        // iconst_m1
    instruction_handlers[0x03] = j2me_handle_iconst;        // iconst_0
    instruction_handlers[0x04] = j2me_handle_iconst;        // iconst_1
    instruction_handlers[0x05] = j2me_handle_iconst;        // iconst_2
    instruction_handlers[0x06] = j2me_handle_iconst;        // iconst_3
    instruction_handlers[0x07] = j2me_handle_iconst;        // iconst_4
    instruction_handlers[0x08] = j2me_handle_iconst;        // iconst_5
    
    // åŠ è½½æŒ‡ä»¤
    instruction_handlers[0x10] = j2me_handle_bipush;        // bipush
    instruction_handlers[0x11] = j2me_handle_sipush;        // sipush
    instruction_handlers[0x15] = j2me_handle_iload;         // iload
    instruction_handlers[0x1a] = j2me_handle_iload;         // iload_0
    instruction_handlers[0x1b] = j2me_handle_iload;         // iload_1
    instruction_handlers[0x1c] = j2me_handle_iload;         // iload_2
    instruction_handlers[0x1d] = j2me_handle_iload;         // iload_3
    instruction_handlers[0x2a] = j2me_handle_aload;         // aload_0
    instruction_handlers[0x2b] = j2me_handle_aload;         // aload_1
    instruction_handlers[0x2c] = j2me_handle_aload;         // aload_2
    instruction_handlers[0x2d] = j2me_handle_aload;         // aload_3
    
    // å­˜å‚¨æŒ‡ä»¤
    instruction_handlers[0x36] = j2me_handle_istore;        // istore
    instruction_handlers[0x3b] = j2me_handle_istore;        // istore_0
    instruction_handlers[0x3c] = j2me_handle_istore;        // istore_1
    instruction_handlers[0x3d] = j2me_handle_istore;        // istore_2
    instruction_handlers[0x3e] = j2me_handle_istore;        // istore_3
    instruction_handlers[0x4b] = j2me_handle_astore;        // astore_0
    instruction_handlers[0x4c] = j2me_handle_astore;        // astore_1
    instruction_handlers[0x4d] = j2me_handle_astore;        // astore_2
    instruction_handlers[0x4e] = j2me_handle_astore;        // astore_3
    
    // æ ˆæ“ä½œæŒ‡ä»¤
    instruction_handlers[0x57] = j2me_handle_pop;           // pop
    instruction_handlers[0x58] = j2me_handle_pop;           // pop2
    instruction_handlers[0x59] = j2me_handle_dup;           // dup
    
    // ç®—æœ¯æŒ‡ä»¤
    instruction_handlers[0x60] = j2me_handle_iadd;          // iadd
    instruction_handlers[0x64] = j2me_handle_isub;          // isub
    instruction_handlers[0x68] = j2me_handle_imul;          // imul
    instruction_handlers[0x6c] = j2me_handle_idiv;          // idiv
    
    // æ§åˆ¶æµæŒ‡ä»¤
    instruction_handlers[0x99] = j2me_handle_ifeq;          // ifeq
    instruction_handlers[0x9a] = j2me_handle_ifne;          // ifne
    instruction_handlers[0xa7] = j2me_handle_goto;          // goto
    
    // è¿”å›æŒ‡ä»¤
    instruction_handlers[0xac] = j2me_handle_ireturn;       // ireturn
    instruction_handlers[0xb1] = j2me_handle_return;        // return
    
    // æ–¹æ³•è°ƒç”¨æŒ‡ä»¤
    instruction_handlers[0xb6] = j2me_handle_invokevirtual; // invokevirtual
    instruction_handlers[0xb7] = j2me_handle_invokespecial; // invokespecial
    instruction_handlers[0xb8] = j2me_handle_invokestatic;  // invokestatic
    
    initialized = true;
}

/**
 * @brief åˆ›å»ºä¼˜åŒ–çš„è§£é‡Šå™¨
 */
j2me_optimized_interpreter_t* j2me_optimized_interpreter_create(size_t code_size) {
    j2me_optimized_interpreter_t* interpreter = 
        (j2me_optimized_interpreter_t*)malloc(sizeof(j2me_optimized_interpreter_t));
    if (!interpreter) {
        return NULL;
    }
    
    memset(interpreter, 0, sizeof(j2me_optimized_interpreter_t));
    
    // åˆ†é…é¢„è§£ç æŒ‡ä»¤æ•°ç»„
    interpreter->predecoded_code = 
        (j2me_predecoded_instruction_t*)malloc(sizeof(j2me_predecoded_instruction_t) * code_size);
    if (!interpreter->predecoded_code) {
        free(interpreter);
        return NULL;
    }
    
    interpreter->code_length = code_size;
    
    // åˆ›å»ºå†…è”ç¼“å­˜
    interpreter->inline_cache = j2me_inline_cache_create(64); // 64ä¸ªç¼“å­˜æ¡ç›®
    if (!interpreter->inline_cache) {
        free(interpreter->predecoded_code);
        free(interpreter);
        return NULL;
    }
    
    // åˆ›å»ºçƒ­ç‚¹æ£€æµ‹å™¨
    interpreter->hotspot_detector = j2me_hotspot_detector_create(1000, 100, 10); // 1000ä¸ªæ–¹æ³•ï¼Œ100ä¸ªå¾ªç¯ï¼Œé˜ˆå€¼10
    if (!interpreter->hotspot_detector) {
        j2me_inline_cache_destroy(interpreter->inline_cache);
        free(interpreter->predecoded_code);
        free(interpreter);
        return NULL;
    }
    
    // åˆ›å»ºæ€§èƒ½ç»Ÿè®¡
    interpreter->stats = j2me_performance_stats_create();
    if (!interpreter->stats) {
        j2me_hotspot_detector_destroy(interpreter->hotspot_detector);
        j2me_inline_cache_destroy(interpreter->inline_cache);
        free(interpreter->predecoded_code);
        free(interpreter);
        return NULL;
    }
    
    // è®¾ç½®é»˜è®¤å‚æ•°
    interpreter->optimization_enabled = true;
    interpreter->batch_size = 100; // é»˜è®¤æ‰¹é‡æ‰§è¡Œ100æ¡æŒ‡ä»¤
    
    // åˆå§‹åŒ–æŒ‡ä»¤å¤„ç†å‡½æ•°è¡¨
    initialize_instruction_handlers();
    
    return interpreter;
}

/**
 * @brief é”€æ¯ä¼˜åŒ–çš„è§£é‡Šå™¨
 */
void j2me_optimized_interpreter_destroy(j2me_optimized_interpreter_t* interpreter) {
    if (interpreter) {
        if (interpreter->predecoded_code) {
            free(interpreter->predecoded_code);
        }
        if (interpreter->inline_cache) {
            j2me_inline_cache_destroy(interpreter->inline_cache);
        }
        if (interpreter->hotspot_detector) {
            j2me_hotspot_detector_destroy(interpreter->hotspot_detector);
        }
        if (interpreter->stats) {
            j2me_performance_stats_destroy(interpreter->stats);
        }
        free(interpreter);
    }
}

/**
 * @brief é¢„è§£ç å­—èŠ‚ç 
 */
j2me_error_t j2me_predecode_bytecode(j2me_optimized_interpreter_t* interpreter,
                                     const j2me_byte* bytecode,
                                     size_t length) {
    if (!interpreter || !bytecode || length == 0) {
        return J2ME_ERROR_INVALID_PARAMETER;
    }
    
    size_t pc = 0;
    size_t instruction_count = 0;
    
    while (pc < length && instruction_count < interpreter->code_length) {
        j2me_predecoded_instruction_t* inst = &interpreter->predecoded_code[instruction_count];
        
        // è¯»å–æ“ä½œç 
        inst->opcode = bytecode[pc++];
        inst->operand_count = 0;
        inst->flags = 0;
        
        // è®¾ç½®æŒ‡ä»¤å¤„ç†å‡½æ•°
        inst->handler = (void*)instruction_handlers[inst->opcode];
        
        // é¢„è§£ææ“ä½œæ•°
        switch (inst->opcode) {
            case 0x10: // bipush
                if (pc < length) {
                    inst->operands[0] = (j2me_byte)bytecode[pc++];
                    inst->operand_count = 1;
                }
                break;
                
            case 0x11: // sipush
                if (pc + 1 < length) {
                    inst->operands[0] = (j2me_short)((bytecode[pc] << 8) | bytecode[pc + 1]);
                    pc += 2;
                    inst->operand_count = 1;
                }
                break;
                
            case 0x15: // iload
            case 0x36: // istore
                if (pc < length) {
                    inst->operands[0] = bytecode[pc++];
                    inst->operand_count = 1;
                }
                break;
                
            case 0x99: // ifeq
            case 0x9a: // ifne
            case 0xa7: // goto
                if (pc + 1 < length) {
                    inst->operands[0] = (j2me_short)((bytecode[pc] << 8) | bytecode[pc + 1]);
                    pc += 2;
                    inst->operand_count = 1;
                    inst->flags |= INST_FLAG_JUMP;
                }
                break;
                
            case 0xb6: // invokevirtual
            case 0xb7: // invokespecial
            case 0xb8: // invokestatic
                if (pc + 1 < length) {
                    inst->operands[0] = (j2me_short)((bytecode[pc] << 8) | bytecode[pc + 1]);
                    pc += 2;
                    inst->operand_count = 1;
                    inst->flags |= INST_FLAG_METHOD_CALL;
                }
                break;
                
            // å¸¸é‡æŒ‡ä»¤é¢„è®¡ç®—
            case 0x02: // iconst_m1
                inst->operands[0] = -1;
                inst->operand_count = 1;
                break;
            case 0x03: case 0x04: case 0x05: case 0x06: case 0x07: case 0x08: // iconst_0 to iconst_5
                inst->operands[0] = inst->opcode - 0x03;
                inst->operand_count = 1;
                break;
                
            // å±€éƒ¨å˜é‡æŒ‡ä»¤é¢„è®¡ç®—ç´¢å¼•
            case 0x1a: case 0x1b: case 0x1c: case 0x1d: // iload_0 to iload_3
                inst->operands[0] = inst->opcode - 0x1a;
                inst->operand_count = 1;
                break;
            case 0x2a: case 0x2b: case 0x2c: case 0x2d: // aload_0 to aload_3
                inst->operands[0] = inst->opcode - 0x2a;
                inst->operand_count = 1;
                break;
            case 0x3b: case 0x3c: case 0x3d: case 0x3e: // istore_0 to istore_3
                inst->operands[0] = inst->opcode - 0x3b;
                inst->operand_count = 1;
                break;
            case 0x4b: case 0x4c: case 0x4d: case 0x4e: // astore_0 to astore_3
                inst->operands[0] = inst->opcode - 0x4b;
                inst->operand_count = 1;
                break;
        }
        
        instruction_count++;
    }
    
    interpreter->code_length = instruction_count;
    return J2ME_SUCCESS;
}

/**
 * @brief ä¼˜åŒ–çš„å­—èŠ‚ç æ‰§è¡Œ
 */
j2me_error_t j2me_execute_optimized(j2me_vm_t* vm,
                                    j2me_stack_frame_t* frame,
                                    j2me_optimized_interpreter_t* interpreter,
                                    j2me_int max_instructions) {
    if (!vm || !frame || !interpreter) {
        return J2ME_ERROR_INVALID_PARAMETER;
    }
    
    // å¼€å§‹æ€§èƒ½ç»Ÿè®¡
    j2me_performance_stats_start(interpreter->stats);
    
    j2me_int executed_instructions = 0;
    j2me_long start_cycles = get_current_time_us();
    
    while (executed_instructions < max_instructions && 
           frame->pc < interpreter->code_length &&
           vm->state == J2ME_VM_RUNNING) {
        
        // æ‰¹é‡æ‰§è¡Œä¼˜åŒ–
        if (interpreter->optimization_enabled) {
            j2me_int batch_executed = j2me_execute_batch(vm, frame, interpreter, 
                                                        frame->pc, interpreter->batch_size);
            executed_instructions += batch_executed;
            
            if (batch_executed == 0) {
                break; // æ‰§è¡Œå®Œæ¯•æˆ–é‡åˆ°é”™è¯¯
            }
        } else {
            // å•æ¡æŒ‡ä»¤æ‰§è¡Œ
            if (frame->pc >= interpreter->code_length) {
                break;
            }
            
            j2me_predecoded_instruction_t* inst = &interpreter->predecoded_code[frame->pc];
            
            if (inst->handler) {
                j2me_instruction_handler_t handler = (j2me_instruction_handler_t)inst->handler;
                j2me_error_t result = handler(vm, frame, inst);
                if (result != J2ME_SUCCESS) {
                    return result;
                }
            }
            
            frame->pc++;
            executed_instructions++;
        }
    }
    
    // è®°å½•æ€§èƒ½ç»Ÿè®¡
    j2me_long end_cycles = get_current_time_us();
    j2me_performance_stats_record_instructions(interpreter->stats, 
                                              executed_instructions, 
                                              end_cycles - start_cycles);
    
    // ç»“æŸæ€§èƒ½ç»Ÿè®¡
    j2me_performance_stats_end(interpreter->stats);
    
    return J2ME_SUCCESS;
}

/**
 * @brief æ‰¹é‡æ‰§è¡ŒæŒ‡ä»¤
 */
j2me_int j2me_execute_batch(j2me_vm_t* vm,
                           j2me_stack_frame_t* frame,
                           j2me_optimized_interpreter_t* interpreter,
                           j2me_int start_pc,
                           j2me_int batch_size) {
    j2me_int executed = 0;
    j2me_int pc = start_pc;
    
    while (executed < batch_size && 
           pc < interpreter->code_length &&
           vm->state == J2ME_VM_RUNNING) {
        
        j2me_predecoded_instruction_t* inst = &interpreter->predecoded_code[pc];
        
        // æ£€æŸ¥æ˜¯å¦æ˜¯è·³è½¬æŒ‡ä»¤ï¼Œå¦‚æœæ˜¯åˆ™ç»“æŸæ‰¹é‡æ‰§è¡Œ
        if (inst->flags & (INST_FLAG_JUMP | INST_FLAG_BRANCH | INST_FLAG_RETURN)) {
            if (inst->handler) {
                frame->pc = pc;
                j2me_instruction_handler_t handler = (j2me_instruction_handler_t)inst->handler;
                j2me_error_t result = handler(vm, frame, inst);
                if (result == J2ME_SUCCESS) {
                    executed++;
                    pc = frame->pc; // è·³è½¬åçš„æ–°PC
                }
            }
            break; // è·³è½¬æŒ‡ä»¤åç»“æŸæ‰¹é‡æ‰§è¡Œ
        }
        
        // æ‰§è¡Œæ™®é€šæŒ‡ä»¤
        if (inst->handler) {
            frame->pc = pc;
            j2me_instruction_handler_t handler = (j2me_instruction_handler_t)inst->handler;
            j2me_error_t result = handler(vm, frame, inst);
            if (result != J2ME_SUCCESS) {
                break;
            }
        }
        
        pc++;
        executed++;
    }
    
    frame->pc = pc;
    return executed;
}

/**
 * @brief åˆ›å»ºå†…è”ç¼“å­˜
 */
j2me_inline_cache_t* j2me_inline_cache_create(size_t capacity) {
    j2me_inline_cache_t* cache = (j2me_inline_cache_t*)malloc(sizeof(j2me_inline_cache_t));
    if (!cache) {
        return NULL;
    }
    
    cache->entries = (j2me_inline_cache_entry_t*)malloc(sizeof(j2me_inline_cache_entry_t) * capacity);
    if (!cache->entries) {
        free(cache);
        return NULL;
    }
    
    memset(cache->entries, 0, sizeof(j2me_inline_cache_entry_t) * capacity);
    cache->size = 0;
    cache->capacity = capacity;
    cache->hit_count = 0;
    cache->miss_count = 0;
    
    return cache;
}

/**
 * @brief é”€æ¯å†…è”ç¼“å­˜
 */
void j2me_inline_cache_destroy(j2me_inline_cache_t* cache) {
    if (cache) {
        if (cache->entries) {
            free(cache->entries);
        }
        free(cache);
    }
}

/**
 * @brief æŸ¥æ‰¾å†…è”ç¼“å­˜
 */
void* j2me_inline_cache_lookup(j2me_inline_cache_t* cache, j2me_int method_ref) {
    if (!cache) {
        return NULL;
    }
    
    // çº¿æ€§æŸ¥æ‰¾ (å¯ä»¥ä¼˜åŒ–ä¸ºå“ˆå¸Œè¡¨)
    for (size_t i = 0; i < cache->size; i++) {
        if (cache->entries[i].method_ref == method_ref) {
            cache->entries[i].call_count++;
            cache->entries[i].last_access_time = get_current_time_us();
            cache->hit_count++;
            return cache->entries[i].target_method;
        }
    }
    
    cache->miss_count++;
    return NULL;
}

/**
 * @brief æ›´æ–°å†…è”ç¼“å­˜
 */
j2me_error_t j2me_inline_cache_update(j2me_inline_cache_t* cache,
                                      j2me_int method_ref,
                                      void* target_method) {
    if (!cache || !target_method) {
        return J2ME_ERROR_INVALID_PARAMETER;
    }
    
    // æŸ¥æ‰¾æ˜¯å¦å·²å­˜åœ¨
    for (size_t i = 0; i < cache->size; i++) {
        if (cache->entries[i].method_ref == method_ref) {
            cache->entries[i].target_method = target_method;
            cache->entries[i].call_count++;
            cache->entries[i].last_access_time = get_current_time_us();
            return J2ME_SUCCESS;
        }
    }
    
    // æ·»åŠ æ–°æ¡ç›®
    if (cache->size < cache->capacity) {
        j2me_inline_cache_entry_t* entry = &cache->entries[cache->size++];
        entry->method_ref = method_ref;
        entry->target_method = target_method;
        entry->call_count = 1;
        entry->last_access_time = get_current_time_us();
        return J2ME_SUCCESS;
    }
    
    // ç¼“å­˜å·²æ»¡ï¼Œæ›¿æ¢æœ€å°‘ä½¿ç”¨çš„æ¡ç›®
    size_t lru_index = 0;
    j2me_long oldest_time = cache->entries[0].last_access_time;
    
    for (size_t i = 1; i < cache->size; i++) {
        if (cache->entries[i].last_access_time < oldest_time) {
            oldest_time = cache->entries[i].last_access_time;
            lru_index = i;
        }
    }
    
    j2me_inline_cache_entry_t* entry = &cache->entries[lru_index];
    entry->method_ref = method_ref;
    entry->target_method = target_method;
    entry->call_count = 1;
    entry->last_access_time = get_current_time_us();
    
    return J2ME_SUCCESS;
}

/**
 * @brief åˆ›å»ºçƒ­ç‚¹æ£€æµ‹å™¨
 */
j2me_hotspot_detector_t* j2me_hotspot_detector_create(size_t method_count,
                                                      size_t loop_count,
                                                      j2me_int hotspot_threshold) {
    j2me_hotspot_detector_t* detector = 
        (j2me_hotspot_detector_t*)malloc(sizeof(j2me_hotspot_detector_t));
    if (!detector) {
        return NULL;
    }
    
    detector->method_counters = (j2me_int*)calloc(method_count, sizeof(j2me_int));
    if (!detector->method_counters) {
        free(detector);
        return NULL;
    }
    
    detector->loop_counters = (j2me_int*)calloc(loop_count, sizeof(j2me_int));
    if (!detector->loop_counters) {
        free(detector->method_counters);
        free(detector);
        return NULL;
    }
    
    detector->method_count = method_count;
    detector->loop_count = loop_count;
    detector->hotspot_threshold = hotspot_threshold;
    detector->compilation_threshold = hotspot_threshold * 10; // ç¼–è¯‘é˜ˆå€¼æ˜¯çƒ­ç‚¹é˜ˆå€¼çš„10å€
    
    return detector;
}

/**
 * @brief é”€æ¯çƒ­ç‚¹æ£€æµ‹å™¨
 */
void j2me_hotspot_detector_destroy(j2me_hotspot_detector_t* detector) {
    if (detector) {
        if (detector->method_counters) {
            free(detector->method_counters);
        }
        if (detector->loop_counters) {
            free(detector->loop_counters);
        }
        free(detector);
    }
}

/**
 * @brief è®°å½•æ–¹æ³•è°ƒç”¨
 */
j2me_boolean j2me_hotspot_record_method_call(j2me_hotspot_detector_t* detector,
                                          j2me_int method_id) {
    if (!detector || method_id < 0 || method_id >= detector->method_count) {
        return false;
    }
    
    detector->method_counters[method_id]++;
    return detector->method_counters[method_id] >= detector->hotspot_threshold;
}

/**
 * @brief è®°å½•å¾ªç¯æ‰§è¡Œ
 */
j2me_boolean j2me_hotspot_record_loop_execution(j2me_hotspot_detector_t* detector,
                                             j2me_int loop_id) {
    if (!detector || loop_id < 0 || loop_id >= detector->loop_count) {
        return false;
    }
    
    detector->loop_counters[loop_id]++;
    return detector->loop_counters[loop_id] >= detector->hotspot_threshold;
}

/**
 * @brief åˆ›å»ºæ€§èƒ½ç»Ÿè®¡
 */
j2me_performance_stats_t* j2me_performance_stats_create(void) {
    j2me_performance_stats_t* stats = 
        (j2me_performance_stats_t*)malloc(sizeof(j2me_performance_stats_t));
    if (!stats) {
        return NULL;
    }
    
    memset(stats, 0, sizeof(j2me_performance_stats_t));
    return stats;
}

/**
 * @brief é”€æ¯æ€§èƒ½ç»Ÿè®¡
 */
void j2me_performance_stats_destroy(j2me_performance_stats_t* stats) {
    if (stats) {
        free(stats);
    }
}

/**
 * @brief å¼€å§‹æ€§èƒ½ç»Ÿè®¡
 */
void j2me_performance_stats_start(j2me_performance_stats_t* stats) {
    if (stats) {
        stats->start_time = get_current_time_us();
    }
}

/**
 * @brief ç»“æŸæ€§èƒ½ç»Ÿè®¡
 */
void j2me_performance_stats_end(j2me_performance_stats_t* stats) {
    if (stats) {
        stats->end_time = get_current_time_us();
    }
}

/**
 * @brief è®°å½•æŒ‡ä»¤æ‰§è¡Œ
 */
void j2me_performance_stats_record_instructions(j2me_performance_stats_t* stats,
                                               j2me_int instruction_count,
                                               j2me_long cycles) {
    if (stats) {
        stats->total_instructions += instruction_count;
        stats->total_cycles += cycles;
    }
}

/**
 * @brief è®°å½•æ–¹æ³•è°ƒç”¨
 */
void j2me_performance_stats_record_method_call(j2me_performance_stats_t* stats) {
    if (stats) {
        stats->method_calls++;
    }
}

/**
 * @brief è®°å½•ç¼“å­˜è®¿é—®
 */
void j2me_performance_stats_record_cache_access(j2me_performance_stats_t* stats,
                                                j2me_boolean hit) {
    if (stats) {
        if (hit) {
            stats->cache_hits++;
        } else {
            stats->cache_misses++;
        }
    }
}

/**
 * @brief æ‰“å°æ€§èƒ½ç»Ÿè®¡æŠ¥å‘Š
 */
void j2me_performance_stats_print_report(j2me_performance_stats_t* stats) {
    if (!stats) {
        return;
    }
    
    j2me_long total_time = stats->end_time - stats->start_time;
    j2me_double instructions_per_second = j2me_performance_stats_get_instructions_per_second(stats);
    j2me_double cache_hit_rate = j2me_performance_stats_get_cache_hit_rate(stats);
    
    printf("\n=== ä¼˜åŒ–è§£é‡Šå™¨æ€§èƒ½ç»Ÿè®¡æŠ¥å‘Š ===\n");
    printf("ğŸ“Š æ‰§è¡Œç»Ÿè®¡:\n");
    printf("   æ€»æŒ‡ä»¤æ•°: %lld\n", stats->total_instructions);
    printf("   æ€»æ‰§è¡Œæ—¶é—´: %lld å¾®ç§’\n", total_time);
    printf("   æ‰§è¡Œé€Ÿåº¦: %.2f MæŒ‡ä»¤/ç§’\n", instructions_per_second / 1000000.0);
    printf("   å¹³å‡æŒ‡ä»¤å»¶è¿Ÿ: %.3f å¾®ç§’\n", 
           total_time > 0 ? (double)stats->total_cycles / stats->total_instructions : 0.0);
    
    printf("\nğŸ“ æ–¹æ³•è°ƒç”¨ç»Ÿè®¡:\n");
    printf("   æ–¹æ³•è°ƒç”¨æ¬¡æ•°: %lld\n", stats->method_calls);
    printf("   å¹³å‡æ¯æ–¹æ³•æŒ‡ä»¤æ•°: %.1f\n", 
           stats->method_calls > 0 ? (double)stats->total_instructions / stats->method_calls : 0.0);
    
    printf("\nğŸ¯ ç¼“å­˜ç»Ÿè®¡:\n");
    printf("   ç¼“å­˜å‘½ä¸­: %lld\n", stats->cache_hits);
    printf("   ç¼“å­˜æœªå‘½ä¸­: %lld\n", stats->cache_misses);
    printf("   ç¼“å­˜å‘½ä¸­ç‡: %.1f%%\n", cache_hit_rate * 100.0);
    
    printf("\nğŸ”¥ çƒ­ç‚¹ç¼–è¯‘ç»Ÿè®¡:\n");
    printf("   çƒ­ç‚¹ç¼–è¯‘æ¬¡æ•°: %lld\n", stats->hotspot_compilations);
    
    printf("\nâš¡ æ€§èƒ½è¯„ä¼°:\n");
    if (instructions_per_second > 500000000) {
        printf("   ğŸŸ¢ æ‰§è¡Œæ€§èƒ½: ä¼˜ç§€ (>500MæŒ‡ä»¤/ç§’)\n");
    } else if (instructions_per_second > 100000000) {
        printf("   ğŸŸ¡ æ‰§è¡Œæ€§èƒ½: è‰¯å¥½ (>100MæŒ‡ä»¤/ç§’)\n");
    } else {
        printf("   ğŸ”´ æ‰§è¡Œæ€§èƒ½: éœ€è¦ä¼˜åŒ– (<100MæŒ‡ä»¤/ç§’)\n");
    }
    
    if (cache_hit_rate > 0.8) {
        printf("   ğŸŸ¢ ç¼“å­˜æ•ˆç‡: ä¼˜ç§€ (>80%%å‘½ä¸­ç‡)\n");
    } else if (cache_hit_rate > 0.6) {
        printf("   ğŸŸ¡ ç¼“å­˜æ•ˆç‡: è‰¯å¥½ (>60%%å‘½ä¸­ç‡)\n");
    } else {
        printf("   ğŸ”´ ç¼“å­˜æ•ˆç‡: éœ€è¦ä¼˜åŒ– (<60%%å‘½ä¸­ç‡)\n");
    }
}

/**
 * @brief è·å–æŒ‡ä»¤æ‰§è¡Œé€Ÿåº¦
 */
j2me_double j2me_performance_stats_get_instructions_per_second(j2me_performance_stats_t* stats) {
    if (!stats || stats->end_time <= stats->start_time) {
        return 0.0;
    }
    
    j2me_long total_time = stats->end_time - stats->start_time;
    return (j2me_double)stats->total_instructions * 1000000.0 / total_time;
}

/**
 * @brief è·å–ç¼“å­˜å‘½ä¸­ç‡
 */
j2me_double j2me_performance_stats_get_cache_hit_rate(j2me_performance_stats_t* stats) {
    if (!stats) {
        return 0.0;
    }
    
    j2me_long total_accesses = stats->cache_hits + stats->cache_misses;
    if (total_accesses == 0) {
        return 0.0;
    }
    
    return (j2me_double)stats->cache_hits / total_accesses;
}

// ============================================================================
// ä¼˜åŒ–çš„æŒ‡ä»¤å¤„ç†å‡½æ•°å®ç°
// ============================================================================

/**
 * @brief å¤„ç†NOPæŒ‡ä»¤
 */
j2me_error_t j2me_handle_nop(j2me_vm_t* vm, j2me_stack_frame_t* frame, j2me_predecoded_instruction_t* inst) {
    // æ— æ“ä½œï¼Œç›´æ¥è¿”å›
    return J2ME_SUCCESS;
}

/**
 * @brief å¤„ç†å¸¸é‡æŒ‡ä»¤ (iconst_*, aconst_null)
 */
j2me_error_t j2me_handle_iconst(j2me_vm_t* vm, j2me_stack_frame_t* frame, j2me_predecoded_instruction_t* inst) {
    j2me_int value = 0;
    
    switch (inst->opcode) {
        case 0x01: // aconst_null
            value = 0;
            break;
        case 0x02: // iconst_m1
            value = -1;
            break;
        case 0x03: case 0x04: case 0x05: case 0x06: case 0x07: case 0x08: // iconst_0 to iconst_5
            value = inst->operands[0]; // é¢„è®¡ç®—çš„å€¼
            break;
        default:
            return J2ME_ERROR_INVALID_STATE;
    }
    
    return j2me_operand_stack_push(&frame->operand_stack, value);
}

/**
 * @brief å¤„ç†BIPUSHæŒ‡ä»¤
 */
j2me_error_t j2me_handle_bipush(j2me_vm_t* vm, j2me_stack_frame_t* frame, j2me_predecoded_instruction_t* inst) {
    return j2me_operand_stack_push(&frame->operand_stack, inst->operands[0]);
}

/**
 * @brief å¤„ç†SIPUSHæŒ‡ä»¤
 */
j2me_error_t j2me_handle_sipush(j2me_vm_t* vm, j2me_stack_frame_t* frame, j2me_predecoded_instruction_t* inst) {
    return j2me_operand_stack_push(&frame->operand_stack, inst->operands[0]);
}

/**
 * @brief å¤„ç†ILOADæŒ‡ä»¤
 */
j2me_error_t j2me_handle_iload(j2me_vm_t* vm, j2me_stack_frame_t* frame, j2me_predecoded_instruction_t* inst) {
    j2me_int index = inst->operands[0]; // é¢„è®¡ç®—çš„ç´¢å¼•
    
    if (index >= frame->local_vars.size) {
        return J2ME_ERROR_INVALID_PARAMETER;
    }
    
    return j2me_operand_stack_push(&frame->operand_stack, frame->local_vars.variables[index]);
}

/**
 * @brief å¤„ç†ALOADæŒ‡ä»¤
 */
j2me_error_t j2me_handle_aload(j2me_vm_t* vm, j2me_stack_frame_t* frame, j2me_predecoded_instruction_t* inst) {
    j2me_int index = inst->operands[0]; // é¢„è®¡ç®—çš„ç´¢å¼•
    
    if (index >= frame->local_vars.size) {
        return J2ME_ERROR_INVALID_PARAMETER;
    }
    
    return j2me_operand_stack_push(&frame->operand_stack, frame->local_vars.variables[index]);
}

/**
 * @brief å¤„ç†ISTOREæŒ‡ä»¤
 */
j2me_error_t j2me_handle_istore(j2me_vm_t* vm, j2me_stack_frame_t* frame, j2me_predecoded_instruction_t* inst) {
    j2me_int index = inst->operands[0]; // é¢„è®¡ç®—çš„ç´¢å¼•
    j2me_int value;
    
    if (index >= frame->local_vars.size) {
        return J2ME_ERROR_INVALID_PARAMETER;
    }
    
    j2me_error_t result = j2me_operand_stack_pop(&frame->operand_stack, &value);
    if (result == J2ME_SUCCESS) {
        frame->local_vars.variables[index] = value;
    }
    
    return result;
}

/**
 * @brief å¤„ç†ASTOREæŒ‡ä»¤
 */
j2me_error_t j2me_handle_astore(j2me_vm_t* vm, j2me_stack_frame_t* frame, j2me_predecoded_instruction_t* inst) {
    j2me_int index = inst->operands[0]; // é¢„è®¡ç®—çš„ç´¢å¼•
    j2me_int value;
    
    if (index >= frame->local_vars.size) {
        return J2ME_ERROR_INVALID_PARAMETER;
    }
    
    j2me_error_t result = j2me_operand_stack_pop(&frame->operand_stack, &value);
    if (result == J2ME_SUCCESS) {
        frame->local_vars.variables[index] = value;
    }
    
    return result;
}

/**
 * @brief å¤„ç†POPæŒ‡ä»¤
 */
j2me_error_t j2me_handle_pop(j2me_vm_t* vm, j2me_stack_frame_t* frame, j2me_predecoded_instruction_t* inst) {
    j2me_int value;
    j2me_error_t result = j2me_operand_stack_pop(&frame->operand_stack, &value);
    
    // POP2æŒ‡ä»¤éœ€è¦å¼¹å‡ºä¸¤ä¸ªå€¼
    if (result == J2ME_SUCCESS && inst->opcode == 0x58) {
        result = j2me_operand_stack_pop(&frame->operand_stack, &value);
    }
    
    return result;
}

/**
 * @brief å¤„ç†DUPæŒ‡ä»¤
 */
j2me_error_t j2me_handle_dup(j2me_vm_t* vm, j2me_stack_frame_t* frame, j2me_predecoded_instruction_t* inst) {
    j2me_int value;
    j2me_error_t result = j2me_operand_stack_pop(&frame->operand_stack, &value);
    
    if (result == J2ME_SUCCESS) {
        // å°†å€¼å‹å›æ ˆä¸¤æ¬¡
        result = j2me_operand_stack_push(&frame->operand_stack, value);
        if (result == J2ME_SUCCESS) {
            result = j2me_operand_stack_push(&frame->operand_stack, value);
        }
    }
    
    return result;
}

/**
 * @brief å¤„ç†IADDæŒ‡ä»¤
 */
j2me_error_t j2me_handle_iadd(j2me_vm_t* vm, j2me_stack_frame_t* frame, j2me_predecoded_instruction_t* inst) {
    j2me_int value1, value2;
    
    j2me_error_t result = j2me_operand_stack_pop(&frame->operand_stack, &value2);
    if (result == J2ME_SUCCESS) {
        result = j2me_operand_stack_pop(&frame->operand_stack, &value1);
        if (result == J2ME_SUCCESS) {
            result = j2me_operand_stack_push(&frame->operand_stack, value1 + value2);
        }
    }
    
    return result;
}

/**
 * @brief å¤„ç†ISUBæŒ‡ä»¤
 */
j2me_error_t j2me_handle_isub(j2me_vm_t* vm, j2me_stack_frame_t* frame, j2me_predecoded_instruction_t* inst) {
    j2me_int value1, value2;
    
    j2me_error_t result = j2me_operand_stack_pop(&frame->operand_stack, &value2);
    if (result == J2ME_SUCCESS) {
        result = j2me_operand_stack_pop(&frame->operand_stack, &value1);
        if (result == J2ME_SUCCESS) {
            result = j2me_operand_stack_push(&frame->operand_stack, value1 - value2);
        }
    }
    
    return result;
}

/**
 * @brief å¤„ç†IMULæŒ‡ä»¤
 */
j2me_error_t j2me_handle_imul(j2me_vm_t* vm, j2me_stack_frame_t* frame, j2me_predecoded_instruction_t* inst) {
    j2me_int value1, value2;
    
    j2me_error_t result = j2me_operand_stack_pop(&frame->operand_stack, &value2);
    if (result == J2ME_SUCCESS) {
        result = j2me_operand_stack_pop(&frame->operand_stack, &value1);
        if (result == J2ME_SUCCESS) {
            result = j2me_operand_stack_push(&frame->operand_stack, value1 * value2);
        }
    }
    
    return result;
}

/**
 * @brief å¤„ç†IDIVæŒ‡ä»¤
 */
j2me_error_t j2me_handle_idiv(j2me_vm_t* vm, j2me_stack_frame_t* frame, j2me_predecoded_instruction_t* inst) {
    j2me_int value1, value2;
    
    j2me_error_t result = j2me_operand_stack_pop(&frame->operand_stack, &value2);
    if (result == J2ME_SUCCESS) {
        result = j2me_operand_stack_pop(&frame->operand_stack, &value1);
        if (result == J2ME_SUCCESS) {
            if (value2 == 0) {
                return J2ME_ERROR_RUNTIME_EXCEPTION; // é™¤é›¶å¼‚å¸¸
            }
            result = j2me_operand_stack_push(&frame->operand_stack, value1 / value2);
        }
    }
    
    return result;
}

/**
 * @brief å¤„ç†IFEQæŒ‡ä»¤
 */
j2me_error_t j2me_handle_ifeq(j2me_vm_t* vm, j2me_stack_frame_t* frame, j2me_predecoded_instruction_t* inst) {
    j2me_int value;
    j2me_error_t result = j2me_operand_stack_pop(&frame->operand_stack, &value);
    
    if (result == J2ME_SUCCESS) {
        if (value == 0) {
            // è·³è½¬åˆ°ç›®æ ‡åœ°å€
            frame->pc += inst->operands[0] - 1; // -1å› ä¸ºPCä¼šåœ¨æ‰¹é‡æ‰§è¡Œåè‡ªå¢
        }
    }
    
    return result;
}

/**
 * @brief å¤„ç†IFNEæŒ‡ä»¤
 */
j2me_error_t j2me_handle_ifne(j2me_vm_t* vm, j2me_stack_frame_t* frame, j2me_predecoded_instruction_t* inst) {
    j2me_int value;
    j2me_error_t result = j2me_operand_stack_pop(&frame->operand_stack, &value);
    
    if (result == J2ME_SUCCESS) {
        if (value != 0) {
            // è·³è½¬åˆ°ç›®æ ‡åœ°å€
            frame->pc += inst->operands[0] - 1; // -1å› ä¸ºPCä¼šåœ¨æ‰¹é‡æ‰§è¡Œåè‡ªå¢
        }
    }
    
    return result;
}

/**
 * @brief å¤„ç†GOTOæŒ‡ä»¤
 */
j2me_error_t j2me_handle_goto(j2me_vm_t* vm, j2me_stack_frame_t* frame, j2me_predecoded_instruction_t* inst) {
    // æ— æ¡ä»¶è·³è½¬
    frame->pc += inst->operands[0] - 1; // -1å› ä¸ºPCä¼šåœ¨æ‰¹é‡æ‰§è¡Œåè‡ªå¢
    return J2ME_SUCCESS;
}

/**
 * @brief å¤„ç†IRETURNæŒ‡ä»¤
 */
j2me_error_t j2me_handle_ireturn(j2me_vm_t* vm, j2me_stack_frame_t* frame, j2me_predecoded_instruction_t* inst) {
    // ä»æ–¹æ³•è¿”å›intå€¼
    // è¿™é‡Œéœ€è¦å®ç°æ–¹æ³•è¿”å›é€»è¾‘
    // æš‚æ—¶ç®€åŒ–å¤„ç†
    frame->pc = 1000000; // è®¾ç½®ä¸€ä¸ªå¤§å€¼æ¥ç»“æŸæ‰§è¡Œ
    return J2ME_SUCCESS;
}

/**
 * @brief å¤„ç†RETURNæŒ‡ä»¤
 */
j2me_error_t j2me_handle_return(j2me_vm_t* vm, j2me_stack_frame_t* frame, j2me_predecoded_instruction_t* inst) {
    // ä»voidæ–¹æ³•è¿”å›
    frame->pc = 1000000; // è®¾ç½®ä¸€ä¸ªå¤§å€¼æ¥ç»“æŸæ‰§è¡Œ
    return J2ME_SUCCESS;
}

/**
 * @brief å¤„ç†INVOKEVIRTUALæŒ‡ä»¤ (ä¼˜åŒ–ç‰ˆæœ¬)
 */
j2me_error_t j2me_handle_invokevirtual(j2me_vm_t* vm, j2me_stack_frame_t* frame, j2me_predecoded_instruction_t* inst) {
    j2me_int method_ref = inst->operands[0];
    
    // å°è¯•ä»å†…è”ç¼“å­˜æŸ¥æ‰¾
    if (vm->optimized_interpreter && vm->optimized_interpreter->inline_cache) {
        void* cached_method = j2me_inline_cache_lookup(vm->optimized_interpreter->inline_cache, method_ref);
        if (cached_method) {
            // ç¼“å­˜å‘½ä¸­ï¼Œç›´æ¥è°ƒç”¨
            j2me_performance_stats_record_cache_access(vm->optimized_interpreter->stats, true);
            // è¿™é‡Œåº”è¯¥è°ƒç”¨ç¼“å­˜çš„æ–¹æ³•
            // æš‚æ—¶ç®€åŒ–å¤„ç†
            return J2ME_SUCCESS;
        } else {
            // ç¼“å­˜æœªå‘½ä¸­ï¼ŒæŸ¥æ‰¾æ–¹æ³•å¹¶æ›´æ–°ç¼“å­˜
            j2me_performance_stats_record_cache_access(vm->optimized_interpreter->stats, false);
            
            // æŸ¥æ‰¾æ–¹æ³• (ç®€åŒ–å®ç°)
            void* target_method = (void*)(intptr_t)method_ref; // ç®€åŒ–çš„æ–¹æ³•æŒ‡é’ˆ
            
            // æ›´æ–°å†…è”ç¼“å­˜
            j2me_inline_cache_update(vm->optimized_interpreter->inline_cache, method_ref, target_method);
        }
    }
    
    // è®°å½•æ–¹æ³•è°ƒç”¨ç»Ÿè®¡
    if (vm->optimized_interpreter && vm->optimized_interpreter->stats) {
        j2me_performance_stats_record_method_call(vm->optimized_interpreter->stats);
    }
    
    // ç®€åŒ–çš„æ–¹æ³•è°ƒç”¨å®ç°
    return J2ME_SUCCESS;
}

/**
 * @brief å¤„ç†INVOKESPECIALæŒ‡ä»¤ (ä¼˜åŒ–ç‰ˆæœ¬)
 */
j2me_error_t j2me_handle_invokespecial(j2me_vm_t* vm, j2me_stack_frame_t* frame, j2me_predecoded_instruction_t* inst) {
    j2me_int method_ref = inst->operands[0];
    
    // è®°å½•æ–¹æ³•è°ƒç”¨ç»Ÿè®¡
    if (vm->optimized_interpreter && vm->optimized_interpreter->stats) {
        j2me_performance_stats_record_method_call(vm->optimized_interpreter->stats);
    }
    
    // ç®€åŒ–çš„ç‰¹æ®Šæ–¹æ³•è°ƒç”¨å®ç°
    return J2ME_SUCCESS;
}

/**
 * @brief å¤„ç†INVOKESTATICæŒ‡ä»¤ (ä¼˜åŒ–ç‰ˆæœ¬)
 */
j2me_error_t j2me_handle_invokestatic(j2me_vm_t* vm, j2me_stack_frame_t* frame, j2me_predecoded_instruction_t* inst) {
    j2me_int method_ref = inst->operands[0];
    
    // é™æ€æ–¹æ³•è°ƒç”¨å¯ä»¥ä½¿ç”¨å†…è”ç¼“å­˜
    if (vm->optimized_interpreter && vm->optimized_interpreter->inline_cache) {
        void* cached_method = j2me_inline_cache_lookup(vm->optimized_interpreter->inline_cache, method_ref);
        if (cached_method) {
            j2me_performance_stats_record_cache_access(vm->optimized_interpreter->stats, true);
        } else {
            j2me_performance_stats_record_cache_access(vm->optimized_interpreter->stats, false);
            
            // æŸ¥æ‰¾é™æ€æ–¹æ³•å¹¶æ›´æ–°ç¼“å­˜
            void* target_method = (void*)(intptr_t)method_ref;
            j2me_inline_cache_update(vm->optimized_interpreter->inline_cache, method_ref, target_method);
        }
    }
    
    // è®°å½•æ–¹æ³•è°ƒç”¨ç»Ÿè®¡
    if (vm->optimized_interpreter && vm->optimized_interpreter->stats) {
        j2me_performance_stats_record_method_call(vm->optimized_interpreter->stats);
    }
    
    // ç®€åŒ–çš„é™æ€æ–¹æ³•è°ƒç”¨å®ç°
    return J2ME_SUCCESS;
}