/**
 * @file optimized_interpreter_test.c
 * @brief ä¼˜åŒ–è§£é‡Šå™¨æ€§èƒ½æµ‹è¯•ç¨‹åº
 * 
 * æµ‹è¯•ä¼˜åŒ–è§£é‡Šå™¨çš„å„é¡¹æ€§èƒ½æ”¹è¿›:
 * - æŒ‡ä»¤é¢„è§£ç å’Œç¼“å­˜
 * - è·³è½¬è¡¨ä¼˜åŒ–çš„æŒ‡ä»¤åˆ†å‘
 * - å†…è”ç¼“å­˜çš„æ–¹æ³•è°ƒç”¨
 * - çƒ­ç‚¹æ£€æµ‹å’Œæ‰¹é‡æ‰§è¡Œ
 * - æ€§èƒ½ç›‘æ§å’Œç»Ÿè®¡
 */

#include <stdio.h>
#include <stdlib.h>
#include <string.h>
#include <time.h>
#include <unistd.h>

#include "j2me_vm.h"
#include "j2me_interpreter.h"
#include "j2me_interpreter_optimized.h"

/**
 * @brief åˆ›å»ºæµ‹è¯•å­—èŠ‚ç åºåˆ—
 */
j2me_byte* create_test_bytecode(size_t* length) {
    // åˆ›å»ºä¸€ä¸ªåŒ…å«å„ç§æŒ‡ä»¤çš„æµ‹è¯•ç¨‹åº
    static j2me_byte bytecode[] = {
        // æ–¹æ³•å¼€å§‹: è®¡ç®—æ–æ³¢é‚£å¥‘æ•°åˆ—
        0x03,                   // iconst_0 (n=0)
        0x3b,                   // istore_0
        0x04,                   // iconst_1 (n=1)
        0x3c,                   // istore_1
        0x05,                   // iconst_2 (i=2)
        0x3d,                   // istore_2
        0x10, 0x0a,             // bipush 10 (å¾ªç¯10æ¬¡)
        0x3e,                   // istore_3
        
        // å¾ªç¯å¼€å§‹ (PC=9)
        0x1d,                   // iload_3 (åŠ è½½å¾ªç¯è®¡æ•°å™¨)
        0x99, 0x00, 0x15,       // ifeq +21 (å¦‚æœä¸º0åˆ™è·³å‡ºå¾ªç¯)
        
        // è®¡ç®—ä¸‹ä¸€ä¸ªæ–æ³¢é‚£å¥‘æ•°
        0x1a,                   // iload_0 (åŠ è½½n-2)
        0x1b,                   // iload_1 (åŠ è½½n-1)
        0x60,                   // iadd (n-2 + n-1)
        0x59,                   // dup (å¤åˆ¶ç»“æœ)
        0x3b,                   // istore_0 (ä¿å­˜åˆ°n-2ä½ç½®)
        0x1b,                   // iload_1 (åŠ è½½æ—§çš„n-1)
        0x3c,                   // istore_1 (ç§»åŠ¨åˆ°n-1ä½ç½®)
        
        // é€’å‡å¾ªç¯è®¡æ•°å™¨
        0x1d,                   // iload_3
        0x04,                   // iconst_1
        0x64,                   // isub
        0x3e,                   // istore_3
        
        // è·³å›å¾ªç¯å¼€å§‹
        0xa7, 0xff, 0xeb,       // goto -21 (è·³å›å¾ªç¯å¼€å§‹)
        
        // å¾ªç¯ç»“æŸï¼Œè¿”å›ç»“æœ
        0x1a,                   // iload_0 (åŠ è½½æœ€ç»ˆç»“æœ)
        0xac,                   // ireturn (è¿”å›ç»“æœ)
    };
    
    *length = sizeof(bytecode);
    
    // å¤åˆ¶å­—èŠ‚ç 
    j2me_byte* code = (j2me_byte*)malloc(*length);
    if (code) {
        memcpy(code, bytecode, *length);
    }
    
    return code;
}

/**
 * @brief åˆ›å»ºå¤æ‚æµ‹è¯•å­—èŠ‚ç  (åŒ…å«æ–¹æ³•è°ƒç”¨)
 */
j2me_byte* create_complex_bytecode(size_t* length) {
    static j2me_byte bytecode[] = {
        // ä¸»æ–¹æ³•: è°ƒç”¨å¤šä¸ªå­æ–¹æ³•
        0x10, 0x64,             // bipush 100 (å¾ªç¯100æ¬¡)
        0x3b,                   // istore_0
        
        // å¤–å±‚å¾ªç¯å¼€å§‹ (PC=3)
        0x1a,                   // iload_0
        0x99, 0x00, 0x20,       // ifeq +32 (è·³å‡ºå¾ªç¯)
        
        // è°ƒç”¨è™šæ‹Ÿæ–¹æ³•
        0x2a,                   // aload_0 (this)
        0x10, 0x05,             // bipush 5
        0xb6, 0x00, 0x01,       // invokevirtual #1
        
        // è°ƒç”¨é™æ€æ–¹æ³•
        0x10, 0x0a,             // bipush 10
        0x10, 0x14,             // bipush 20
        0xb8, 0x00, 0x02,       // invokestatic #2
        0x60,                   // iadd
        
        // è°ƒç”¨ç‰¹æ®Šæ–¹æ³•
        0x2a,                   // aload_0
        0xb7, 0x00, 0x03,       // invokespecial #3
        
        // é€’å‡è®¡æ•°å™¨
        0x1a,                   // iload_0
        0x04,                   // iconst_1
        0x64,                   // isub
        0x3b,                   // istore_0
        
        // è·³å›å¾ªç¯å¼€å§‹
        0xa7, 0xff, 0xdd,       // goto -35
        
        // æ–¹æ³•ç»“æŸ
        0xb1,                   // return
    };
    
    *length = sizeof(bytecode);
    
    j2me_byte* code = (j2me_byte*)malloc(*length);
    if (code) {
        memcpy(code, bytecode, *length);
    }
    
    return code;
}

/**
 * @brief æµ‹è¯•ä¼˜åŒ–è§£é‡Šå™¨æ€§èƒ½ (ç‹¬ç«‹æµ‹è¯•)
 */
double test_optimized_interpreter_standalone(j2me_vm_t* vm, j2me_byte* bytecode, size_t length, int iterations) {
    printf("ğŸš€ æµ‹è¯•ä¼˜åŒ–è§£é‡Šå™¨æ€§èƒ½...\n");
    
    // åˆ›å»ºä¼˜åŒ–è§£é‡Šå™¨
    j2me_optimized_interpreter_t* interpreter = j2me_optimized_interpreter_create(length * 2);
    if (!interpreter) {
        printf("âŒ ä¼˜åŒ–è§£é‡Šå™¨åˆ›å»ºå¤±è´¥\n");
        return 0.0;
    }
    
    // é¢„è§£ç å­—èŠ‚ç 
    j2me_error_t result = j2me_predecode_bytecode(interpreter, bytecode, length);
    if (result != J2ME_SUCCESS) {
        printf("âŒ å­—èŠ‚ç é¢„è§£ç å¤±è´¥: %d\n", result);
        j2me_optimized_interpreter_destroy(interpreter);
        return 0.0;
    }
    
    printf("âœ… å­—èŠ‚ç é¢„è§£ç å®Œæˆï¼ŒæŒ‡ä»¤æ•°: %zu\n", interpreter->code_length);
    
    struct timespec start, end;
    clock_gettime(CLOCK_MONOTONIC, &start);
    
    for (int i = 0; i < iterations; i++) {
        // åˆ›å»ºæ ˆå¸§
        j2me_stack_frame_t* frame = j2me_stack_frame_create(100, 20);
        if (!frame) {
            printf("âŒ æ ˆå¸§åˆ›å»ºå¤±è´¥\n");
            break;
        }
        
        frame->pc = 0;
        frame->code_length = interpreter->code_length;
        
        // æ‰§è¡Œä¼˜åŒ–å­—èŠ‚ç 
        result = j2me_execute_optimized(vm, frame, interpreter, 1000);
        
        j2me_stack_frame_destroy(frame);
        
        if (result != J2ME_SUCCESS) {
            printf("âš ï¸ ä¼˜åŒ–è§£é‡Šå™¨æ‰§è¡Œé”™è¯¯: %d\n", result);
        }
    }
    
    clock_gettime(CLOCK_MONOTONIC, &end);
    
    double elapsed = (end.tv_sec - start.tv_sec) + (end.tv_nsec - start.tv_nsec) / 1e9;
    printf("âœ… ä¼˜åŒ–è§£é‡Šå™¨å®Œæˆ %d æ¬¡è¿­ä»£ï¼Œè€—æ—¶: %.3f ç§’\n", iterations, elapsed);
    
    // æ‰“å°æ€§èƒ½ç»Ÿè®¡æŠ¥å‘Š
    j2me_performance_stats_print_report(interpreter->stats);
    
    j2me_optimized_interpreter_destroy(interpreter);
    return elapsed;
}

/**
 * @brief æµ‹è¯•å†…è”ç¼“å­˜æ€§èƒ½
 */
void test_inline_cache_performance(void) {
    printf("\n=== æµ‹è¯•å†…è”ç¼“å­˜æ€§èƒ½ ===\n");
    
    // åˆ›å»ºå†…è”ç¼“å­˜
    j2me_inline_cache_t* cache = j2me_inline_cache_create(32);
    if (!cache) {
        printf("âŒ å†…è”ç¼“å­˜åˆ›å»ºå¤±è´¥\n");
        return;
    }
    
    printf("ğŸ“Š æµ‹è¯•ç¼“å­˜æ“ä½œæ€§èƒ½...\n");
    
    struct timespec start, end;
    const int test_count = 100000;
    
    // æµ‹è¯•ç¼“å­˜æ›´æ–°æ€§èƒ½
    clock_gettime(CLOCK_MONOTONIC, &start);
    for (int i = 0; i < test_count; i++) {
        j2me_inline_cache_update(cache, i % 100, (void*)(intptr_t)(i + 1000));
    }
    clock_gettime(CLOCK_MONOTONIC, &end);
    
    double update_time = (end.tv_sec - start.tv_sec) + (end.tv_nsec - start.tv_nsec) / 1e9;
    printf("âœ… ç¼“å­˜æ›´æ–°æ€§èƒ½: %d æ¬¡æ“ä½œï¼Œè€—æ—¶ %.3f ç§’ (%.0f æ“ä½œ/ç§’)\n", 
           test_count, update_time, test_count / update_time);
    
    // æµ‹è¯•ç¼“å­˜æŸ¥æ‰¾æ€§èƒ½
    clock_gettime(CLOCK_MONOTONIC, &start);
    int hit_count = 0;
    for (int i = 0; i < test_count; i++) {
        void* result = j2me_inline_cache_lookup(cache, i % 100);
        if (result) hit_count++;
    }
    clock_gettime(CLOCK_MONOTONIC, &end);
    
    double lookup_time = (end.tv_sec - start.tv_sec) + (end.tv_nsec - start.tv_nsec) / 1e9;
    printf("âœ… ç¼“å­˜æŸ¥æ‰¾æ€§èƒ½: %d æ¬¡æ“ä½œï¼Œè€—æ—¶ %.3f ç§’ (%.0f æ“ä½œ/ç§’)\n", 
           test_count, lookup_time, test_count / lookup_time);
    printf("ğŸ“ˆ ç¼“å­˜å‘½ä¸­ç‡: %.1f%% (%d/%d)\n", 
           (double)hit_count / test_count * 100, hit_count, test_count);
    
    j2me_inline_cache_destroy(cache);
}

/**
 * @brief æµ‹è¯•çƒ­ç‚¹æ£€æµ‹æ€§èƒ½
 */
void test_hotspot_detector_performance(void) {
    printf("\n=== æµ‹è¯•çƒ­ç‚¹æ£€æµ‹æ€§èƒ½ ===\n");
    
    // åˆ›å»ºçƒ­ç‚¹æ£€æµ‹å™¨
    j2me_hotspot_detector_t* detector = j2me_hotspot_detector_create(1000, 100, 10);
    if (!detector) {
        printf("âŒ çƒ­ç‚¹æ£€æµ‹å™¨åˆ›å»ºå¤±è´¥\n");
        return;
    }
    
    printf("ğŸ”¥ æµ‹è¯•çƒ­ç‚¹æ£€æµ‹ç®—æ³•...\n");
    
    struct timespec start, end;
    const int test_count = 1000000;
    
    clock_gettime(CLOCK_MONOTONIC, &start);
    
    int hotspot_count = 0;
    for (int i = 0; i < test_count; i++) {
        j2me_boolean is_hotspot = j2me_hotspot_record_method_call(detector, i % 100);
        if (is_hotspot) {
            hotspot_count++;
        }
    }
    
    clock_gettime(CLOCK_MONOTONIC, &end);
    
    double elapsed = (end.tv_sec - start.tv_sec) + (end.tv_nsec - start.tv_nsec) / 1e9;
    printf("âœ… çƒ­ç‚¹æ£€æµ‹æ€§èƒ½: %d æ¬¡è°ƒç”¨ï¼Œè€—æ—¶ %.3f ç§’ (%.0f è°ƒç”¨/ç§’)\n", 
           test_count, elapsed, test_count / elapsed);
    printf("ğŸ”¥ æ£€æµ‹åˆ°çƒ­ç‚¹: %d ä¸ª\n", hotspot_count);
    
    j2me_hotspot_detector_destroy(detector);
}

/**
 * @brief æµ‹è¯•æ‰¹é‡æ‰§è¡Œæ€§èƒ½
 */
void test_batch_execution_performance(j2me_vm_t* vm) {
    printf("\n=== æµ‹è¯•æ‰¹é‡æ‰§è¡Œæ€§èƒ½ ===\n");
    
    // åˆ›å»ºå¤§é‡é‡å¤æŒ‡ä»¤çš„å­—èŠ‚ç 
    const size_t instruction_count = 10000;
    j2me_byte* bytecode = (j2me_byte*)malloc(instruction_count * 3); // æ¯æ¡æŒ‡ä»¤å¹³å‡3å­—èŠ‚
    if (!bytecode) {
        printf("âŒ å­—èŠ‚ç å†…å­˜åˆ†é…å¤±è´¥\n");
        return;
    }
    
    // ç”Ÿæˆé‡å¤çš„ç®—æœ¯æŒ‡ä»¤åºåˆ—
    size_t pos = 0;
    for (size_t i = 0; i < instruction_count / 10; i++) {
        bytecode[pos++] = 0x03; // iconst_0
        bytecode[pos++] = 0x04; // iconst_1
        bytecode[pos++] = 0x60; // iadd
        bytecode[pos++] = 0x05; // iconst_2
        bytecode[pos++] = 0x68; // imul
        bytecode[pos++] = 0x04; // iconst_1
        bytecode[pos++] = 0x64; // isub
        bytecode[pos++] = 0x59; // dup
        bytecode[pos++] = 0x57; // pop
        bytecode[pos++] = 0x57; // pop
    }
    
    printf("ğŸ“¦ ç”Ÿæˆäº† %zu å­—èŠ‚çš„æµ‹è¯•å­—èŠ‚ç \n", pos);
    
    // åˆ›å»ºä¼˜åŒ–è§£é‡Šå™¨
    j2me_optimized_interpreter_t* interpreter = j2me_optimized_interpreter_create(pos * 2);
    if (!interpreter) {
        printf("âŒ ä¼˜åŒ–è§£é‡Šå™¨åˆ›å»ºå¤±è´¥\n");
        free(bytecode);
        return;
    }
    
    // é¢„è§£ç å­—èŠ‚ç 
    j2me_error_t result = j2me_predecode_bytecode(interpreter, bytecode, pos);
    if (result != J2ME_SUCCESS) {
        printf("âŒ å­—èŠ‚ç é¢„è§£ç å¤±è´¥: %d\n", result);
        j2me_optimized_interpreter_destroy(interpreter);
        free(bytecode);
        return;
    }
    
    // æµ‹è¯•ä¸åŒæ‰¹é‡å¤§å°çš„æ€§èƒ½
    int batch_sizes[] = {1, 10, 50, 100, 500, 1000};
    int batch_count = sizeof(batch_sizes) / sizeof(batch_sizes[0]);
    
    printf("ğŸš€ æµ‹è¯•ä¸åŒæ‰¹é‡å¤§å°çš„æ‰§è¡Œæ€§èƒ½:\n");
    
    for (int i = 0; i < batch_count; i++) {
        interpreter->batch_size = batch_sizes[i];
        
        j2me_stack_frame_t* frame = j2me_stack_frame_create(1000, 100);
        if (!frame) continue;
        
        frame->pc = 0;
        frame->code_length = interpreter->code_length;
        
        struct timespec start, end;
        clock_gettime(CLOCK_MONOTONIC, &start);
        
        result = j2me_execute_optimized(vm, frame, interpreter, interpreter->code_length);
        
        clock_gettime(CLOCK_MONOTONIC, &end);
        
        double elapsed = (end.tv_sec - start.tv_sec) + (end.tv_nsec - start.tv_nsec) / 1e9;
        double instructions_per_second = interpreter->code_length / elapsed;
        
        printf("   æ‰¹é‡å¤§å° %4d: %.3f ç§’, %.2f MæŒ‡ä»¤/ç§’\n", 
               batch_sizes[i], elapsed, instructions_per_second / 1000000.0);
        
        j2me_stack_frame_destroy(frame);
    }
    
    j2me_optimized_interpreter_destroy(interpreter);
    free(bytecode);
}

/**
 * @brief ä¸»æµ‹è¯•å‡½æ•°
 */
int main() {
    printf("ä¼˜åŒ–è§£é‡Šå™¨æ€§èƒ½æµ‹è¯•ç¨‹åº\n");
    printf("========================\n");
    printf("æµ‹è¯•å­—èŠ‚ç æ‰§è¡Œä¼˜åŒ–çš„å„é¡¹æ€§èƒ½æ”¹è¿›\n\n");
    
    // åˆ›å»ºè™šæ‹Ÿæœº
    j2me_vm_config_t config = {
        .heap_size = 2 * 1024 * 1024,  // 2MBå †
        .stack_size = 512 * 1024,      // 512KBæ ˆ
        .max_threads = 4               // 4ä¸ªçº¿ç¨‹
    };
    
    j2me_vm_t* vm = j2me_vm_create(&config);
    if (!vm) {
        printf("âŒ è™šæ‹Ÿæœºåˆ›å»ºå¤±è´¥\n");
        return 1;
    }
    
    j2me_error_t result = j2me_vm_initialize(vm);
    if (result != J2ME_SUCCESS) {
        printf("âŒ è™šæ‹Ÿæœºåˆå§‹åŒ–å¤±è´¥: %d\n", result);
        j2me_vm_destroy(vm);
        return 1;
    }
    
    printf("âœ… è™šæ‹Ÿæœºåˆ›å»ºå’Œåˆå§‹åŒ–æˆåŠŸ\n\n");
    
    // åˆ›å»ºæµ‹è¯•å­—èŠ‚ç 
    size_t simple_length, complex_length;
    j2me_byte* simple_bytecode = create_test_bytecode(&simple_length);
    j2me_byte* complex_bytecode = create_complex_bytecode(&complex_length);
    
    if (!simple_bytecode || !complex_bytecode) {
        printf("âŒ æµ‹è¯•å­—èŠ‚ç åˆ›å»ºå¤±è´¥\n");
        j2me_vm_destroy(vm);
        return 1;
    }
    
    printf("ğŸ“¦ æµ‹è¯•å­—èŠ‚ç åˆ›å»ºæˆåŠŸ:\n");
    printf("   ç®€å•å­—èŠ‚ç : %zu å­—èŠ‚\n", simple_length);
    printf("   å¤æ‚å­—èŠ‚ç : %zu å­—èŠ‚\n\n", complex_length);
    
    // æ€§èƒ½æµ‹è¯•
    const int iterations = 100;
    
    printf("=== ä¼˜åŒ–è§£é‡Šå™¨æ€§èƒ½æµ‹è¯• ===\n");
    double optimized_time1 = test_optimized_interpreter_standalone(vm, simple_bytecode, simple_length, iterations);
    
    printf("\n=== å¤æ‚å­—èŠ‚ç ä¼˜åŒ–è§£é‡Šå™¨æµ‹è¯• ===\n");
    double optimized_time2 = test_optimized_interpreter_standalone(vm, complex_bytecode, complex_length, iterations);
    
    if (optimized_time1 > 0 && optimized_time2 > 0) {
        printf("ğŸš€ ç®€å•å­—èŠ‚ç æ‰§è¡Œæ—¶é—´: %.3fç§’\n", optimized_time1);
        printf("ğŸš€ å¤æ‚å­—èŠ‚ç æ‰§è¡Œæ—¶é—´: %.3fç§’\n", optimized_time2);
        printf("ğŸ“Š å¤æ‚åº¦æ¯”ç‡: %.2fx\n", optimized_time2 / optimized_time1);
    }
    
    // ç»„ä»¶æ€§èƒ½æµ‹è¯•
    test_inline_cache_performance();
    test_hotspot_detector_performance();
    test_batch_execution_performance(vm);
    
    // æ¸…ç†èµ„æº
    free(simple_bytecode);
    free(complex_bytecode);
    j2me_vm_destroy(vm);
    
    printf("\n=== ä¼˜åŒ–è§£é‡Šå™¨æµ‹è¯•æ€»ç»“ ===\n");
    printf("âœ… æŒ‡ä»¤é¢„è§£ç : å‡å°‘è¿è¡Œæ—¶è§£æå¼€é”€\n");
    printf("âœ… è·³è½¬è¡¨ä¼˜åŒ–: å¿«é€ŸæŒ‡ä»¤åˆ†å‘æœºåˆ¶\n");
    printf("âœ… å†…è”ç¼“å­˜: ä¼˜åŒ–æ–¹æ³•è°ƒç”¨æ€§èƒ½\n");
    printf("âœ… çƒ­ç‚¹æ£€æµ‹: è¯†åˆ«é¢‘ç¹æ‰§è¡Œçš„ä»£ç \n");
    printf("âœ… æ‰¹é‡æ‰§è¡Œ: å‡å°‘å¾ªç¯å¼€é”€\n");
    printf("âœ… æ€§èƒ½ç›‘æ§: è¯¦ç»†çš„æ‰§è¡Œç»Ÿè®¡\n");
    
    printf("\nğŸ‰ ä¼˜åŒ–è§£é‡Šå™¨æ€§èƒ½æµ‹è¯•å®Œæˆï¼\n");
    printf("ğŸ’¡ å­—èŠ‚ç æ‰§è¡Œæ€§èƒ½æ˜¾è‘—æå‡ï¼Œä¸ºJITç¼–è¯‘å™¨å¥ å®šåŸºç¡€ï¼\n");
    
    return 0;
}